{
  "locked": true,
  "version": -9996,
  "targets": {
    "DNXCore,Version=v5.0": {
      "System.Private.Uri/4.0.0-beta-23011": {
        "runtime": {
          "lib/DNXCore50/System.Private.Uri.dll": {}
        }
      },
      "System.Runtime/4.0.20-beta-23011": {
        "dependencies": {
          "System.Private.Uri": "4.0.0-beta-23011"
        },
        "compile": {
          "ref/dotnet/System.Runtime.dll": {}
        },
        "runtime": {
          "lib/DNXCore50/System.Runtime.dll": {}
        }
      }
    }
  },
  "libraries": {
    "System.Private.Uri/4.0.0-beta-23011": {
      "sha512": "yil581lvQfpXUFfLnfmS7t9+NDvy7NeSHfKYBF7CluatvDQxT6QmwRxi9zKXzCYB7OY6sqvrRFOgdeAxNalVkA==",
      "files": [
        "System.Private.Uri.4.0.0-beta-23011.nupkg",
        "System.Private.Uri.4.0.0-beta-23011.nupkg.sha512",
        "System.Private.Uri.nuspec",
        "lib/DNXCore50/System.Private.Uri.dll",
        "lib/netcore50/System.Private.Uri.dll",
        "ref/dnxcore50/_._",
        "ref/netcore50/_._",
        "runtimes/win8-aot/lib/netcore50/System.Private.Uri.dll"
      ]
    },
    "System.Runtime/4.0.20-beta-23011": {
      "sha512": "WFRsJnfRzXYIiDJRbTXGctncx6Hw1F/uS2c5a5CzUwHuA3D/CM152F2HjWt12dLgH0BOcGvcRjKl2AfJ6MnHVg==",
      "files": [
        "System.Runtime.4.0.20-beta-23011.nupkg",
        "System.Runtime.4.0.20-beta-23011.nupkg.sha512",
        "System.Runtime.nuspec",
        "lib/DNXCore50/System.Runtime.dll",
        "lib/net46/_._",
        "lib/netcore50/System.Runtime.dll",
        "ref/dotnet/System.Runtime.dll",
        "ref/net46/_._",
        "runtimes/win8-aot/lib/netcore50/System.Runtime.dll"
      ]
    }
  },
  "projectFileDependencyGroups": {
    "": [
      "System.Runtime >= 4.0.20-beta-*"
    ],
    "DNXCore,Version=v5.0": []
  }
}